[
 {
  "algolia_id": "2670564002",
  "allow_alternative_item": 0,
  "asset_category": null,
  "asset_naming_series": null,
  "attributes": [],
  "auto_create_assets": 0,
  "barcodes": [],
  "batch_number_series": null,
  "brand": null,
  "country_of_origin": "India",
  "create_new_batch": 0,
  "customer": null,
  "customer_code": "",
  "customer_items": [],
  "customs_tariff_number": null,
  "default_bom": null,
  "default_item_manufacturer": null,
  "default_manufacturer_part_no": null,
  "default_material_request_type": "Purchase",
  "deferred_expense_account": null,
  "deferred_revenue_account": null,
  "delivered_by_supplier": 0,
  "description": "Cheese",
  "disabled": 0,
  "docstatus": 0,
  "doctype": "Item",
  "enable_deferred_expense": 0,
  "enable_deferred_revenue": 0,
  "end_of_life": "2099-12-31",
  "gst_hsn_code": null,
  "has_batch_no": 0,
  "has_expiry_date": 0,
  "has_serial_no": 0,
  "has_variants": 0,
  "hub_category_to_publish": null,
  "hub_sync_id": null,
  "hub_warehouse": null,
  "image": null,
  "include_item_in_manufacturing": 1,
  "inspection_required_before_delivery": 0,
  "inspection_required_before_purchase": 0,
  "is_customer_provided_item": 0,
  "is_fixed_asset": 0,
  "is_item_from_hub": 0,
  "is_nil_exempt": 0,
  "is_non_gst": 0,
  "is_purchase_item": 1,
  "is_sales_item": 1,
  "is_stock_item": 1,
  "is_sub_contracted_item": 0,
  "item_code": "XX!",
  "item_defaults": [],
  "item_group": "Consumable",
  "item_name": "Cheese",
  "last_purchase_rate": 0.0,
  "lead_time_days": 0,
  "max_discount": 0.0,
  "min_order_qty": 0.0,
  "modified": "2021-06-28 14:06:02.407326",
  "name": "XX!",
  "naming_series": "STO-ITEM-.YYYY.-",
  "no_of_months": 0,
  "no_of_months_exp": 0,
  "opening_stock": 0.0,
  "over_billing_allowance": 0.0,
  "over_delivery_receipt_allowance": 0.0,
  "parent": null,
  "parentfield": null,
  "parenttype": null,
  "publish_in_hub": 0,
  "purchase_uom": null,
  "quality_inspection_template": null,
  "reorder_levels": [],
  "retain_sample": 0,
  "route": "consumable/cheese-v86kd",
  "safety_stock": 0.0,
  "sales_uom": null,
  "sample_quantity": 0,
  "serial_no_series": null,
  "shelf_life_in_days": 0,
  "show_in_website": 0,
  "show_variant_in_website": 0,
  "slideshow": null,
  "standard_rate": 0.0,
  "stock_uom": "Unit",
  "supplier_items": [],
  "synced_with_hub": 0,
  "taxes": [],
  "thumbnail": null,
  "total_projected_qty": 0.0,
  "uoms": [
   {
    "conversion_factor": 1.0,
    "parent": "XX!",
    "parentfield": "uoms",
    "parenttype": "Item",
    "uom": "Unit"
   }
  ],
  "valuation_method": "",
  "valuation_rate": 0.0,
  "variant_based_on": "Item Attribute",
  "variant_of": null,
  "warranty_period": null,
  "web_long_description": null,
  "website_content": null,
  "website_image": null,
  "website_image_alt": null,
  "website_item_groups": [],
  "website_specifications": [],
  "website_warehouse": null,
  "weight_per_unit": 0.0,
  "weight_uom": null,
  "weightage": 0
 },
 {
  "algolia_id": "2670593002",
  "allow_alternative_item": 0,
  "asset_category": null,
  "asset_naming_series": null,
  "attributes": [],
  "auto_create_assets": 0,
  "barcodes": [],
  "batch_number_series": null,
  "brand": null,
  "country_of_origin": "India",
  "create_new_batch": 0,
  "customer": null,
  "customer_code": "",
  "customer_items": [],
  "customs_tariff_number": null,
  "default_bom": null,
  "default_item_manufacturer": null,
  "default_manufacturer_part_no": null,
  "default_material_request_type": "Purchase",
  "deferred_expense_account": null,
  "deferred_revenue_account": null,
  "delivered_by_supplier": 0,
  "description": "Yogurt",
  "disabled": 0,
  "docstatus": 0,
  "doctype": "Item",
  "enable_deferred_expense": 0,
  "enable_deferred_revenue": 0,
  "end_of_life": "2099-12-31",
  "gst_hsn_code": null,
  "has_batch_no": 0,
  "has_expiry_date": 0,
  "has_serial_no": 0,
  "has_variants": 0,
  "hub_category_to_publish": null,
  "hub_sync_id": null,
  "hub_warehouse": null,
  "image": null,
  "include_item_in_manufacturing": 1,
  "inspection_required_before_delivery": 0,
  "inspection_required_before_purchase": 0,
  "is_customer_provided_item": 0,
  "is_fixed_asset": 0,
  "is_item_from_hub": 0,
  "is_nil_exempt": 0,
  "is_non_gst": 0,
  "is_purchase_item": 1,
  "is_sales_item": 1,
  "is_stock_item": 1,
  "is_sub_contracted_item": 0,
  "item_code": "XX3",
  "item_defaults": [],
  "item_group": "Consumable",
  "item_name": "Fresh Cream",
  "last_purchase_rate": 0.0,
  "lead_time_days": 0,
  "max_discount": 0.0,
  "min_order_qty": 0.0,
  "modified": "2021-06-28 14:05:33.556253",
  "name": "XX3",
  "naming_series": "STO-ITEM-.YYYY.-",
  "no_of_months": 0,
  "no_of_months_exp": 0,
  "opening_stock": 0.0,
  "over_billing_allowance": 0.0,
  "over_delivery_receipt_allowance": 0.0,
  "parent": null,
  "parentfield": null,
  "parenttype": null,
  "publish_in_hub": 0,
  "purchase_uom": null,
  "quality_inspection_template": null,
  "reorder_levels": [],
  "retain_sample": 0,
  "route": "consumable/fresh-cream-fqof9",
  "safety_stock": 0.0,
  "sales_uom": null,
  "sample_quantity": 0,
  "serial_no_series": null,
  "shelf_life_in_days": 0,
  "show_in_website": 1,
  "show_variant_in_website": 0,
  "slideshow": null,
  "standard_rate": 0.0,
  "stock_uom": "Nos",
  "supplier_items": [],
  "synced_with_hub": 0,
  "taxes": [],
  "thumbnail": null,
  "total_projected_qty": 0.0,
  "uoms": [
   {
    "conversion_factor": 1.0,
    "parent": "XX3",
    "parentfield": "uoms",
    "parenttype": "Item",
    "uom": "Nos"
   }
  ],
  "valuation_method": "",
  "valuation_rate": 0.0,
  "variant_based_on": "Item Attribute",
  "variant_of": null,
  "warranty_period": null,
  "web_long_description": null,
  "website_content": null,
  "website_image": null,
  "website_image_alt": null,
  "website_item_groups": [],
  "website_specifications": [],
  "website_warehouse": null,
  "weight_per_unit": 0.0,
  "weight_uom": null,
  "weightage": 0
 },
 {
  "algolia_id": "2674961001",
  "allow_alternative_item": 0,
  "asset_category": null,
  "asset_naming_series": null,
  "attributes": [],
  "auto_create_assets": 0,
  "barcodes": [],
  "batch_number_series": null,
  "brand": null,
  "country_of_origin": "India",
  "create_new_batch": 0,
  "customer": null,
  "customer_code": "",
  "customer_items": [],
  "customs_tariff_number": null,
  "default_bom": null,
  "default_item_manufacturer": null,
  "default_manufacturer_part_no": null,
  "default_material_request_type": "Purchase",
  "deferred_expense_account": null,
  "deferred_revenue_account": null,
  "delivered_by_supplier": 0,
  "description": "Butter",
  "disabled": 0,
  "docstatus": 0,
  "doctype": "Item",
  "enable_deferred_expense": 0,
  "enable_deferred_revenue": 0,
  "end_of_life": "2099-12-31",
  "gst_hsn_code": null,
  "has_batch_no": 0,
  "has_expiry_date": 0,
  "has_serial_no": 0,
  "has_variants": 0,
  "hub_category_to_publish": null,
  "hub_sync_id": null,
  "hub_warehouse": null,
  "image": null,
  "include_item_in_manufacturing": 1,
  "inspection_required_before_delivery": 0,
  "inspection_required_before_purchase": 0,
  "is_customer_provided_item": 0,
  "is_fixed_asset": 0,
  "is_item_from_hub": 0,
  "is_nil_exempt": 0,
  "is_non_gst": 0,
  "is_purchase_item": 1,
  "is_sales_item": 1,
  "is_stock_item": 1,
  "is_sub_contracted_item": 0,
  "item_code": "XX4",
  "item_defaults": [],
  "item_group": "Consumable",
  "item_name": "Butter",
  "last_purchase_rate": 0.0,
  "lead_time_days": 0,
  "max_discount": 0.0,
  "min_order_qty": 0.0,
  "modified": "2021-06-28 14:04:36.542649",
  "name": "XX4",
  "naming_series": "STO-ITEM-.YYYY.-",
  "no_of_months": 0,
  "no_of_months_exp": 0,
  "opening_stock": 0.0,
  "over_billing_allowance": 0.0,
  "over_delivery_receipt_allowance": 0.0,
  "parent": null,
  "parentfield": null,
  "parenttype": null,
  "publish_in_hub": 0,
  "purchase_uom": null,
  "quality_inspection_template": null,
  "reorder_levels": [],
  "retain_sample": 0,
  "route": "consumable/butter-0fwnm",
  "safety_stock": 0.0,
  "sales_uom": null,
  "sample_quantity": 0,
  "serial_no_series": null,
  "shelf_life_in_days": 0,
  "show_in_website": 1,
  "show_variant_in_website": 0,
  "slideshow": null,
  "standard_rate": 0.0,
  "stock_uom": "Box",
  "supplier_items": [],
  "synced_with_hub": 0,
  "taxes": [],
  "thumbnail": null,
  "total_projected_qty": 0.0,
  "uoms": [
   {
    "conversion_factor": 1.0,
    "parent": "XX4",
    "parentfield": "uoms",
    "parenttype": "Item",
    "uom": "Box"
   }
  ],
  "valuation_method": "",
  "valuation_rate": 0.0,
  "variant_based_on": "Item Attribute",
  "variant_of": null,
  "warranty_period": null,
  "web_long_description": null,
  "website_content": null,
  "website_image": null,
  "website_image_alt": null,
  "website_item_groups": [],
  "website_specifications": [],
  "website_warehouse": null,
  "weight_per_unit": 0.0,
  "weight_uom": null,
  "weightage": 0
 },
 {
  "algolia_id": "6656795000",
  "allow_alternative_item": 0,
  "asset_category": null,
  "asset_naming_series": null,
  "attributes": [
   {
    "attribute": "Colour",
    "attribute_value": "",
    "from_range": 0.0,
    "increment": 0.0,
    "numeric_values": 0,
    "parent": "T XX1",
    "parentfield": "attributes",
    "parenttype": "Item",
    "to_range": 0.0,
    "variant_of": null
   }
  ],
  "auto_create_assets": 0,
  "barcodes": [],
  "batch_number_series": null,
  "brand": null,
  "country_of_origin": "India",
  "create_new_batch": 0,
  "customer": null,
  "customer_code": "",
  "customer_items": [],
  "customs_tariff_number": null,
  "default_bom": null,
  "default_item_manufacturer": null,
  "default_manufacturer_part_no": null,
  "default_material_request_type": "Purchase",
  "deferred_expense_account": null,
  "deferred_revenue_account": null,
  "delivered_by_supplier": 0,
  "description": "T shirt",
  "disabled": 0,
  "docstatus": 0,
  "doctype": "Item",
  "enable_deferred_expense": 0,
  "enable_deferred_revenue": 0,
  "end_of_life": "2099-12-31",
  "gst_hsn_code": null,
  "has_batch_no": 0,
  "has_expiry_date": 0,
  "has_serial_no": 0,
  "has_variants": 1,
  "hub_category_to_publish": null,
  "hub_sync_id": null,
  "hub_warehouse": null,
  "image": "/files/white.jpeg",
  "include_item_in_manufacturing": 1,
  "inspection_required_before_delivery": 0,
  "inspection_required_before_purchase": 0,
  "is_customer_provided_item": 0,
  "is_fixed_asset": 0,
  "is_item_from_hub": 0,
  "is_nil_exempt": 0,
  "is_non_gst": 0,
  "is_purchase_item": 1,
  "is_sales_item": 1,
  "is_stock_item": 1,
  "is_sub_contracted_item": 0,
  "item_code": "T XX1",
  "item_defaults": [],
  "item_group": "All Item Groups",
  "item_name": "T shirt",
  "last_purchase_rate": 0.0,
  "lead_time_days": 0,
  "max_discount": 0.0,
  "min_order_qty": 0.0,
  "modified": "2021-06-28 14:41:19.858781",
  "name": "T XX1",
  "naming_series": "STO-ITEM-.YYYY.-",
  "no_of_months": 0,
  "no_of_months_exp": 0,
  "opening_stock": 0.0,
  "over_billing_allowance": 0.0,
  "over_delivery_receipt_allowance": 0.0,
  "parent": null,
  "parentfield": null,
  "parenttype": null,
  "publish_in_hub": 0,
  "purchase_uom": null,
  "quality_inspection_template": null,
  "reorder_levels": [],
  "retain_sample": 0,
  "route": null,
  "safety_stock": 0.0,
  "sales_uom": null,
  "sample_quantity": 0,
  "serial_no_series": null,
  "shelf_life_in_days": 0,
  "show_in_website": 0,
  "show_variant_in_website": 0,
  "slideshow": null,
  "standard_rate": 299.0,
  "stock_uom": "Nos",
  "supplier_items": [],
  "synced_with_hub": 0,
  "taxes": [],
  "thumbnail": "/files/white_small.jpeg",
  "total_projected_qty": 0.0,
  "uoms": [
   {
    "conversion_factor": 1.0,
    "parent": "T XX1",
    "parentfield": "uoms",
    "parenttype": "Item",
    "uom": "Nos"
   }
  ],
  "valuation_method": "",
  "valuation_rate": 0.0,
  "variant_based_on": "Item Attribute",
  "variant_of": null,
  "warranty_period": null,
  "web_long_description": null,
  "website_content": null,
  "website_image": "/files/white.jpeg",
  "website_image_alt": null,
  "website_item_groups": [],
  "website_specifications": [],
  "website_warehouse": null,
  "weight_per_unit": 0.0,
  "weight_uom": null,
  "weightage": 0
 }
]